pwrstat/__init__.py
pwrstat/cli.py
pwrstat/main.py
pwrstat/parser.py
pwrstat_api-0.0.1.dist-info/METADATA
pwrstat_api-0.0.1.dist-info/WHEEL
pwrstat_api-0.0.1.dist-info/entry_points.txt
pwrstat_api-0.0.1.dist-info/top_level.txt
pwrstat_api-0.0.1.dist-info/RECORD
