Metadata-Version: 2.4
Name: pwrstat-api
Version: 0.0.1
Summary: A FastAPI API to get the status of a CyberPower UPS.
Author-email: unkwn1 <unkwn1@unkwn1.dev>
Requires-Python: >=3.8
Requires-Dist: fastapi
Requires-Dist: uvicorn[standard]
Requires-Dist: pydantic
